odoo9_addon_openeducat_hostel-9.0.2.4.0-py2.7-nspkg.pth
odoo_addons/openeducat_hostel/__openerp__.py
odoo_addons/openeducat_hostel/hostel_menu.xml
odoo_addons/openeducat_hostel/__init__.py
odoo_addons/openeducat_hostel/security/ir.model.access.csv
odoo_addons/openeducat_hostel/models/hostel_room.py
odoo_addons/openeducat_hostel/models/__init__.py
odoo_addons/openeducat_hostel/models/facility_line.py
odoo_addons/openeducat_hostel/models/room.py
odoo_addons/openeducat_hostel/models/hostel.py
odoo_addons/openeducat_hostel/i18n/openeducat_hostel.pot
odoo_addons/openeducat_hostel/views/hostel_view.xml
odoo_addons/openeducat_hostel/views/hostel_room_view.xml
odoo_addons/openeducat_hostel/views/room_view.xml
odoo_addons/openeducat_hostel/demo/op.hostel.csv
odoo_addons/openeducat_hostel/demo/op.room.csv
odoo_addons/openeducat_hostel/demo/op.hostel.room.csv
odoo_addons/openeducat_hostel/static/description/openeducat_logo.png
odoo_addons/openeducat_hostel/static/description/hostel.png
odoo_addons/openeducat_hostel/static/description/index.html
odoo_addons/openeducat_hostel/static/description/hostel_room_allocation.png
odoo_addons/openeducat_hostel/static/description/openeducat_hostel_banner.jpg
odoo_addons/openeducat_hostel/static/description/icon.png
odoo9_addon_openeducat_hostel-9.0.2.4.0.dist-info/top_level.txt
odoo9_addon_openeducat_hostel-9.0.2.4.0.dist-info/WHEEL
odoo9_addon_openeducat_hostel-9.0.2.4.0.dist-info/RECORD
odoo9_addon_openeducat_hostel-9.0.2.4.0.dist-info/metadata.json
odoo9_addon_openeducat_hostel-9.0.2.4.0.dist-info/DESCRIPTION.rst
odoo9_addon_openeducat_hostel-9.0.2.4.0.dist-info/METADATA
odoo9_addon_openeducat_hostel-9.0.2.4.0.dist-info/namespace_packages.txt
